{
	"page":0,
	"records":4,
	"total":1,
	"rows":[{"id":"0","invdate":"dasfdsf","name":"fsdf000","amount":"6651","tax":"651dsf","total":"65160","notes":"651651"},
	{"id":"1","invdate":"dasfdsf","name":"fsdf000","amount":"6651","tax":"651dsf","total":"65160","notes":"651651"},
	{"id":"2","invdate":"dasfdsf","name":"fsdf000","amount":"6651","tax":"651dsf","total":"65160","notes":"651651"},
	{"id":"3","invdate":"dasfdsf","name":"fsdf000","amount":"6651","tax":"651dsf","total":"65160","notes":"651651"}]
}
